setup.cfg
setup.py
RPIRateMyProfessors/RPIRateMyProfessors.py
RPIRateMyProfessors/__init__.py
RPIRateMyProfessors.egg-info/PKG-INFO
RPIRateMyProfessors.egg-info/SOURCES.txt
RPIRateMyProfessors.egg-info/dependency_links.txt
RPIRateMyProfessors.egg-info/top_level.txt
RPIRateMyProfessors.egg-info/zip-safe