Metadata-Version: 1.1
Name: RPIRateMyProfessors
Version: 0.1.0dev
Summary: some RPI RateMyProfessor functionality
Home-page: http://pythonhosted.org/RPIRateMyProfessors
Author: linksapprentice1
Author-email: linksapprentice1@gmail.com
License: MIT
Keywords: RPI RateMyProfessors RPIRateMyProfessors
Platform: UNKNOWN
Classifier: Topic :: Utilities
